beci/metadata.py
beci/cli/__init__.py
beci-0.0.1.dist-info/METADATA
beci-0.0.1.dist-info/WHEEL
beci-0.0.1.dist-info/entry_points.txt
beci-0.0.1.dist-info/RECORD
