Metadata-Version: 2.3
Name: beci
Version: 0.0.1
Summary: A helper script for the beci project
Project-URL: Documentation, https://gitlab.jsc.fz-juelich.de/exacb/beci
Project-URL: Issues, https://gitlab.jsc.fz-juelich.de/exacb/beci
Project-URL: Source, https://gitlab.jsc.fz-juelich.de/exacb/beci
Author-email: Jayesh Badwaik <j.badwaik@fz-juelich.de>
Requires-Dist: semver
